gofilepy/__init__.py
gofilepy/gofile.py
gofilepy-0.3.2.dist-info/METADATA
gofilepy-0.3.2.dist-info/WHEEL
gofilepy-0.3.2.dist-info/entry_points.txt
gofilepy-0.3.2.dist-info/RECORD
